bassmodeldiffusion/__init__.py
bassmodeldiffusion/base/__init__.py
bassmodeldiffusion/base/base.py
bassmodeldiffusion/modeling/__init__.py
bassmodeldiffusion/modeling/modeling.py
bassmodeldiffusion/visualize/__init__.py
bassmodeldiffusion/visualize/visualize.py
bassmodeldiffusion-0.1.0.dist-info/AUTHORS.rst
bassmodeldiffusion-0.1.0.dist-info/LICENSE
bassmodeldiffusion-0.1.0.dist-info/METADATA
bassmodeldiffusion-0.1.0.dist-info/WHEEL
bassmodeldiffusion-0.1.0.dist-info/top_level.txt
bassmodeldiffusion-0.1.0.dist-info/RECORD
