Metadata-Version: 2.1
Name: bassmodeldiffusion
Version: 0.1.0
Home-page: https://github.com/ilynmark/bassmodeldiffusion
Author: Maria Miskaryan
Author-email: mar.miskaryan@gmail.com
License: MIT license
Keywords: bassmodeldiffusion
Classifier: Development Status :: 2 - Pre-Alpha
Classifier: Intended Audience :: Developers
Classifier: License :: OSI Approved :: MIT License
Classifier: Natural Language :: English
Classifier: Programming Language :: Python :: 3.10
Requires-Python: >=3.6
License-File: LICENSE
License-File: AUTHORS.rst
Requires-Dist: numpy (==1.24.3)
Requires-Dist: pandas (==2.0.1)
Requires-Dist: matplotlib (==3.7.1)
Requires-Dist: statsmodels (==0.14.0)
